[
    {
        "IPO Name":"Amagi Media Labs",
        "Type_sub":"Mainboard",
        "Day":"Closed",
        "QIB":33.13,
        "NII":38.26,
        "Retail":"9.54",
        "Total":30.24,
        "Normalized_IPO_Name":"Amagi Media Labs",
        "Stock \/ IPO":"Amagi Media Labs",
        "IPO GMP":27.0,
        "IPO Price":361.0,
        "Listing Gain":7.48,
        "Review":"May Apply",
        "Date":"13-16 Jan",
        "Type_gmp":"Mainboard"
    },
    {
        "IPO Name":"Aritas Vinyl",
        "Type_sub":"SME",
        "Day":"1",
        "QIB":0.0,
        "NII":0.8,
        "Retail":"0.26",
        "Total":0.47,
        "Normalized_IPO_Name":"Aritas Vinyl",
        "Stock \/ IPO":"Aritas Vinyl",
        "IPO GMP":10.0,
        "IPO Price":47.0,
        "Listing Gain":21.28,
        "Review":"Neutral",
        "Date":"16-20 Jan",
        "Type_gmp":"SME"
    },
    {
        "IPO Name":"Armour Security",
        "Type_sub":"SME",
        "Day":"2",
        "QIB":1.0,
        "NII":0.6,
        "Retail":"0.38",
        "Total":0.5,
        "Normalized_IPO_Name":"Armour Security",
        "Stock \/ IPO":"Armour Security",
        "IPO GMP":4.0,
        "IPO Price":57.0,
        "Listing Gain":7.02,
        "Review":"Neutral",
        "Date":"14-19 Jan",
        "Type_gmp":"SME"
    },
    {
        "IPO Name":"Avana Electrosystems",
        "Type_sub":"SME",
        "Day":"Closed",
        "QIB":54.97,
        "NII":219.02,
        "Retail":"137.52",
        "Total":131.82,
        "Normalized_IPO_Name":"Avana Electrosystems",
        "Stock \/ IPO":"Avana Electrosystems",
        "IPO GMP":13.0,
        "IPO Price":59.0,
        "Listing Gain":22.03,
        "Review":"Neutral",
        "Date":"12-14 Jan",
        "Type_gmp":"SME"
    },
    {
        "IPO Name":"Defrail Technologies",
        "Type_sub":"SME",
        "Day":"Closed",
        "QIB":71.09,
        "NII":160.95,
        "Retail":"101.28",
        "Total":105.54,
        "Normalized_IPO_Name":"Defrail Technologies",
        "Stock \/ IPO":"Defrail Technologies",
        "IPO GMP":10.0,
        "IPO Price":74.0,
        "Listing Gain":13.51,
        "Review":"Neutral",
        "Date":"9-13 Jan",
        "Type_gmp":"SME"
    },
    {
        "IPO Name":"Digilogic Systems",
        "Type_sub":"SME",
        "Day":"20-22 Jan",
        "QIB":0.0,
        "NII":0.0,
        "Retail":"0.00",
        "Total":0.0,
        "Normalized_IPO_Name":"Digilogic Systems",
        "Stock \/ IPO":"Digilogic Systems",
        "IPO GMP":5.0,
        "IPO Price":104.0,
        "Listing Gain":4.81,
        "Review":"\u2013",
        "Date":"20-22 Jan",
        "Type_gmp":"SME"
    },
    {
        "IPO Name":"GRE Renew Enertech",
        "Type_sub":"SME",
        "Day":"Closed",
        "QIB":14.69,
        "NII":24.67,
        "Retail":"14.10",
        "Total":16.53,
        "Normalized_IPO_Name":"GRE Renew Enertech",
        "Stock \/ IPO":"GRE Renew Enertech",
        "IPO GMP":7.0,
        "IPO Price":105.0,
        "Listing Gain":6.67,
        "Review":"Neutral",
        "Date":"13-16 Jan",
        "Type_gmp":"SME"
    },
    {
        "IPO Name":"INDO SMC",
        "Type_sub":"SME",
        "Day":"Closed",
        "QIB":94.94,
        "NII":164.59,
        "Retail":"96.13",
        "Total":110.49,
        "Normalized_IPO_Name":"INDO SMC",
        "Stock \/ IPO":"INDO SMC",
        "IPO GMP":32.0,
        "IPO Price":149.0,
        "Listing Gain":21.48,
        "Review":"Neutral",
        "Date":"13-16 Jan",
        "Type_gmp":"SME"
    },
    {
        "IPO Name":"KRM Ayurveda",
        "Type_sub":"SME",
        "Day":"21-23 Jan",
        "QIB":0.0,
        "NII":0.0,
        "Retail":"0.00",
        "Total":0.0,
        "Normalized_IPO_Name":"KRM Ayurveda",
        "Stock \/ IPO":"KRM Ayurveda",
        "IPO GMP":18.0,
        "IPO Price":135.0,
        "Listing Gain":13.33,
        "Review":"\u2013",
        "Date":"21-23 Jan",
        "Type_gmp":"SME"
    },
    {
        "IPO Name":"Shadowfax",
        "Type_sub":"Mainboard",
        "Day":"20-22 Jan",
        "QIB":0.0,
        "NII":0.0,
        "Retail":"0.00",
        "Total":0.0,
        "Normalized_IPO_Name":"Shadowfax",
        "Stock \/ IPO":"Shadowfax",
        "IPO GMP":16.0,
        "IPO Price":124.0,
        "Listing Gain":12.9,
        "Review":"Neutral",
        "Date":"20-22 Jan",
        "Type_gmp":"Mainboard"
    },
    {
        "IPO Name":"Shayona Engineering",
        "Type_sub":"SME",
        "Day":"22-27 Jan",
        "QIB":0.0,
        "NII":0.0,
        "Retail":"0.00",
        "Total":0.0,
        "Normalized_IPO_Name":"Shayona Engineering",
        "Stock \/ IPO":"Shayona Engineering",
        "IPO GMP":0.0,
        "IPO Price":null,
        "Listing Gain":null,
        "Review":"\u2013",
        "Date":"22-27 Jan",
        "Type_gmp":"SME"
    }
]