[
    {
        "Company":"Accretion Nutraveda",
        "IPO Type":"SME",
        "Closing Date":"Closed",
        "QIB":1.01,
        "NII(X)":"2.08",
        "Retail":"2.19",
        "Total":1.83,
        "Normalized_IPO_Name":"Accretion Nutraveda",
        "Stock \/ IPO":"Accretion Nutraveda",
        "IPO GMP":16,
        "IPO Price":129.0,
        "Listing Gain":12.4,
        "Review":"Neutral",
        "Date":"28-30 Jan",
        "Type":"SME"
    },
    {
        "Company":"Biopol Chemicals",
        "IPO Type":"SME",
        "Closing Date":"10 Feb",
        "QIB":0.0,
        "NII(X)":"0.00",
        "Retail":"0.00",
        "Total":0.0,
        "Normalized_IPO_Name":"Biopol Chemicals",
        "Stock \/ IPO":"Biopol Chemicals",
        "IPO GMP":0,
        "IPO Price":108.0,
        "Listing Gain":null,
        "Review":"Neutral",
        "Date":"6-10 Feb",
        "Type":"SME"
    },
    {
        "Company":"Brandman Retail",
        "IPO Type":"SME",
        "Closing Date":"6 Feb",
        "QIB":0.0,
        "NII(X)":"0.00",
        "Retail":"0.00",
        "Total":0.0,
        "Normalized_IPO_Name":"Brandman Retail",
        "Stock \/ IPO":"Brandman Retail",
        "IPO GMP":0,
        "IPO Price":176.0,
        "Listing Gain":null,
        "Review":"\u2013",
        "Date":"4-6 Feb",
        "Type":"SME"
    },
    {
        "Company":"CKK Retail Mart",
        "IPO Type":"SME",
        "Closing Date":"3 Feb",
        "QIB":1.12,
        "NII(X)":"0.80",
        "Retail":"0.71",
        "Total":0.86,
        "Normalized_IPO_Name":"CKK Retail Mart",
        "Stock \/ IPO":"CKK Retail Mart",
        "IPO GMP":0,
        "IPO Price":163.0,
        "Listing Gain":null,
        "Review":"Neutral",
        "Date":"30-3 Feb",
        "Type":"SME"
    },
    {
        "Company":"Grover Jewells",
        "IPO Type":"SME",
        "Closing Date":"6 Feb",
        "QIB":0.0,
        "NII(X)":"0.00",
        "Retail":"0.00",
        "Total":0.0,
        "Normalized_IPO_Name":"Grover Jewells",
        "Stock \/ IPO":"Grover Jewells",
        "IPO GMP":0,
        "IPO Price":88.0,
        "Listing Gain":null,
        "Review":"Neutral",
        "Date":"4-6 Feb",
        "Type":"SME"
    },
    {
        "Company":"Kanishk Aluminium",
        "IPO Type":"SME",
        "Closing Date":"Closed",
        "QIB":0.0,
        "NII(X)":"0.23",
        "Retail":"1.86",
        "Total":1.04,
        "Normalized_IPO_Name":"Kanishk Aluminium",
        "Stock \/ IPO":"Kanishk Aluminium",
        "IPO GMP":4,
        "IPO Price":73.0,
        "Listing Gain":5.47,
        "Review":"Neutral",
        "Date":"28-30 Jan",
        "Type":"SME"
    },
    {
        "Company":"Kasturi Metal Composite",
        "IPO Type":"SME",
        "Closing Date":"Closed",
        "QIB":4.0,
        "NII(X)":"38.88",
        "Retail":"16.49",
        "Total":17.75,
        "Normalized_IPO_Name":"Kasturi Metal Composite",
        "Stock \/ IPO":"Kasturi Metal Composite",
        "IPO GMP":0,
        "IPO Price":64.0,
        "Listing Gain":null,
        "Review":"\u2013",
        "Date":"27-29 Jan",
        "Type":"SME"
    },
    {
        "Company":"Msafe Equipments",
        "IPO Type":"SME",
        "Closing Date":"Closed",
        "QIB":117.97,
        "NII(X)":"308.23",
        "Retail":"133.16",
        "Total":166.72,
        "Normalized_IPO_Name":"Msafe Equipments",
        "Stock \/ IPO":"Msafe Equipments",
        "IPO GMP":20,
        "IPO Price":123.0,
        "Listing Gain":16.26,
        "Review":"Neutral",
        "Date":"28-30 Jan",
        "Type":"SME"
    },
    {
        "Company":"NFP Sampoorna Foods",
        "IPO Type":"SME",
        "Closing Date":"6 Feb",
        "QIB":0.0,
        "NII(X)":"0.00",
        "Retail":"0.00",
        "Total":0.0,
        "Normalized_IPO_Name":"NFP Sampoorna Foods",
        "Stock \/ IPO":"NFP Sampoorna Foods",
        "IPO GMP":0,
        "IPO Price":55.0,
        "Listing Gain":null,
        "Review":"Neutral",
        "Date":"4-6 Feb",
        "Type":"SME"
    }
]